LICENSE.txt
setup.py
RakwanCul.egg-info/PKG-INFO
RakwanCul.egg-info/SOURCES.txt
RakwanCul.egg-info/dependency_links.txt
RakwanCul.egg-info/top_level.txt
code/__init__.py