Metadata-Version: 2.1
Name: RakwanCul
Version: 0.1
Summary: Simple library in python for test
Author: Rakwan-Ali
Classifier: Programming Language :: Python :: 3
Classifier: Operating System :: OS Independent
Classifier: License :: OSI Approved :: MIT License
License-File: LICENSE.txt
